cursofiap/__init__.py
cursofiap/core.py
cursofiap_vbrito-1.0.0.dist-info/METADATA
cursofiap_vbrito-1.0.0.dist-info/WHEEL
cursofiap_vbrito-1.0.0.dist-info/top_level.txt
cursofiap_vbrito-1.0.0.dist-info/RECORD
